ProteinNetworks/R_requests.py
ProteinNetworks/STRING_enrichment.py
ProteinNetworks/__init__.py
ProteinNetworks/enrichment.py
ProteinNetworks/interactions.py
ProteinNetworks/mapping.py
ProteinNetworks/networks.py
ProteinNetworks/wrappers.py
ProteinNetworks/BioGRID/additionalIdentifierTypes.list
ProteinNetworks/BioGRID/biogridpyrc
ProteinNetworks/BioGRID/evidenceList.list
ProteinNetworks/RScripts/Prioretizing_GO.R
ProteinNetworks/RScripts/check_packages.R
ProteinNetworks-0.1.5.dist-info/LICENSE
ProteinNetworks-0.1.5.dist-info/METADATA
ProteinNetworks-0.1.5.dist-info/WHEEL
ProteinNetworks-0.1.5.dist-info/top_level.txt
ProteinNetworks-0.1.5.dist-info/RECORD
