Metadata-Version: 2.1
Name: ProteinNetworks
Version: 0.1.5
Summary: Module for working with protein networks (gene ontology, enrichment, protein-protein interactions, etc.)
Home-page: https://github.com/skewer33/ProteinNetworks.git
Author: Mokin Yakov
Author-email: mokinyakov@mail.ru
Project-URL: Documentation, https://github.com/skewer33/ProteinNetworks/blob/main/README.md
Keywords: proteins interactions PPI networks enrichment STRINGdb Bioilogical-Processes Molecular-Functions Cellular-Components Gene-Ontology
Classifier: Programming Language :: Python :: 3.12
Classifier: License :: OSI Approved :: MIT License
Classifier: Operating System :: OS Independent
Requires-Python: >=3.7
License-File: LICENSE
Requires-Dist: pandas >=2.0.1
Requires-Dist: stringdb ==0.1.5
Requires-Dist: tabulate ==0.9.0
Requires-Dist: umap-learn >=0.5.2
Requires-Dist: networkx >=3.4.1
Requires-Dist: matplotlib >=3.9.1
Requires-Dist: biogridpy ==0.1.1
